notionize/__init__.py
notionize/converters.py
notionize/enums.py
notionize/errors.py
notionize/main.py
notionize/models.py
notionize/py.typed
notionize-0.2.4.dist-info/METADATA
notionize-0.2.4.dist-info/WHEEL
notionize-0.2.4.dist-info/licenses/LICENSE
notionize-0.2.4.dist-info/RECORD
