Metadata-Version: 2.4
Name: notionize
Version: 0.2.4
Summary: Add your description here
License-File: LICENSE
Requires-Python: >=3.10
Requires-Dist: mistune>=2.0.0
Requires-Dist: pydantic>=2.1
